Workbook

Sheet Cover
B2: 3-STATEMENT MODEL BUILD INSTRUCTIONS
B3: By Kristen Gallagher
B5: 1. GET DATA | F5: RULES:
B7: 1 | C7: Go to sec.gov/cgi-bin/browse-edgar | F7: Every query starts with let and ends with in Output
B8: 2 | C8: Search "Company Name" or ticker | F8: Every line except the last ends with a comma
B9: 3 | C9: Filter to Annual Reports (10-K) | F9: Tag names are case sensitive; must match exactly
B10: 4 | C10: Click the most recent 10-K filing | F10: Only one "in" statement at the very end
B11: 5 | C11: Click Sections: Item 8: Financial Statements to review the raw data | F11: TO CHANGE COMPANY:
B13: 2. SET UP POWER QUERY IN EXCEL | F13: Replace CIK number in the URL with the new company's CIK from EDGAR. Everything else stays the same.
B15: 1 | C15: Open Excel
B16: 2 | C16: Click Data tab
B17: 3 | C17: Click Get Data (Power Query)
B18: 4 | C18: Click Blank Query
B19: 5 | C19: Click Advanced Editor
B20: 6 | C20: Delete everything in the editor
B22: 3. WRITE THE QUERY
B24: 1 | C24: The SEC stores all financial data in a JSON file at:
B25: 2 | C25: https://data.sec.gov/api/xbrl/companyfacts/CIK0001823945.json
B26: 3 | C26: Every line item follows the same 4-step pattern:
C28: a) Get list:
C29: XList = Table.FromList(GAAP[TagName][units][USD], Splitter.SplitByNothing(), {"Record"})
C30: b) Expand fields:
C31: XExp = Table.ExpandRecordColumn(XList, "Record", {"end", "val", "form", "fp"}, {"Date", "Value", "Form", "Period"})
C32: c) Filter for annual only:
C33: XAnnual = Table.SelectRows(XExp, each [Form] = "10-K" and [Period] = "FY")
C34: d) Label it:
C35: XFinal = Table.AddColumn(XAnnual, "Metric", each "NameLabel")
C36: XFinal2 = Table.Distinct(XFinal, {"Date"})
B38: 4. PULL TAGS
C40: Income Statement: | D40: Balance Sheet:
C41: Revenues | D41: Assets
C42: NetIncomeLoss | D42: Liabilities
C43: OperatingIncomeLoss | D43: LongTermDebt
C44: LaborAndRelatedExpense | D44: StockholdersEquity
C45: GeneralAndAdministrativeExpense | D45: CashAndCashEquivalentsAtCarryingValue
C46: AmortizationOfIntangibleAssets | D46: Cash Flow:
C47: InterestExpense | D47: NetCashProvidedByUsedInOperatingActivities
C48: IncomeTaxExpenseBenefit | D48: NetCashProvidedByUsedInInvestingActivities
D49: NetCashProvidedByUsedInFinancingActivities
B51: 5. LOAD DATA INTO EXCEL
B52: 1 | C52: Click Done in Advanced Editor
B53: 2 | C53: Click Close & Load in the Power Query ribbon
B54: 3 | C54: Data loads into a new sheet as a table with three columns: Metric, Date, Value
B56: 6. PIVOT THE DATA
B57: 1 | C57: Select all loaded data
B58: 2 | C58: Insert → PivotTable
B59: 3 | C59: Put Date in Columns
B60: 4 | C60: Put Metric in Rows
B61: 5 | C61: Put Value in Values
B62: 6 | C62: This gives you years as columns, metrics as rows: standard financial statement layout
B64: 7. NEXT STEPS TO BUILD
C66: Still to build:
C68: Assumptions: revenue growth %, compensation %, tax rate, interest rate
C69: Supporting Schedules — debt schedule, D&A schedule
C70: Credit Ratios tab: Debt/EBITDA, interest coverage, net income margin, revenue growth
C71: Dashboard; charts, flags for deteriorating metrics
C72: Macros: auto-refresh, flag deteriorating credits, generate summary report

Sheet STMT
D2: Historical Period | K2: Forecasted Period
C3: Blue Owl Capital (OWL) | D3: 2019-12-31 | E3: 2020-12-31 | F3: 2021-12-31 | G3: 2022-12-31 | H3: 2023-12-31 | I3: 2024-12-31 | J3: 2025-12-31 | K3: 46387 | L3: 46752 | M3: 47118 | N3: 47483 | O3: 47848
C4: Dollars in Thousands, Except Per Share Data | D4: =IF(E78=0, "ok", "X") -> X | E4: =IF(F78=0, "ok", "X") -> ok | F4: =IF(G78=0, "ok", "X") -> ok | G4: =IF(H78=0, "ok", "X") -> ok | H4: =IF(I78=0, "ok", "X") -> ok | I4: =IF(J78=0, "ok", "X") -> ok | J4: =IF(K78=0, "ok", "X") -> ok
C6: Assumptions
C8: Growth Rate
C10: Revenue Growth (% Change) | E10: =(E22-D22)/E22 -> 0.23603467 | F10: =(F22-E22)/F22 -> 0.69678156 | G10: =(G22-F22)/G22 -> 0.39850714 | H10: =(H22-G22)/H22 -> 0.20898841 | I10: =(I22-H22)/I22 -> 0.24562707 | J10: =(J22-I22)/J22 -> 0.20024925 | M10: AUM Growth: 40% by 2028
C11: Compensation (% of Revenue) | E11: =ABS(D25/D22) -> 0.58565889 | F11: =ABS(E25/E22) -> 0.96363709 | G11: =ABS(F25/F22) -> 1.817002 | H11: =ABS(G25/G22) -> 0.65318802 | I11: =ABS(H25/H22) -> 0.50279393 | J11: =ABS(I25/I22) -> 0.44326524 | M11: AUM: $251B → $500B+ by 2029 : 2x+ growth, ~15% CAGR
C12: General & Administrative (% of Revenue) | E12: =ABS(D27/D22) -> 0.27094577 | F12: =ABS(E27/E22) -> 0.27144487 | G12: =ABS(F27/F22) -> 0.17025336 | H12: =ABS(G27/G22) -> 0.16106188 | I12: =ABS(H27/H22) -> 0.14022169 | J12: =ABS(I27/I22) -> 0.17989289 | M12: FRE Management Fees: $2.0B → $5.1B+ by 2029 : 20%+ CAGR
C13: Depreciation & Amortization (% of Revenue) | E13: =ABS(D26/D22) -> 0 | F13: =ABS(E26/E22) -> 0 | G13: =ABS(F26/F22) -> 0.13823527 | H13: =ABS(G26/G22) -> 0.18756288 | I13: =ABS(H26/H22) -> 0.1734463 | J13: =ABS(I26/I22) -> 0.11250891 | M13: Fee Related Earnings: $1.3B → $3.1B+ by 2029 : 20%+ CAGR
C14: Interest (% of Debt) | E14: =D34/D28 -> 0.040750414 | F14: =E34/E28 -> 0.077188843 | G14: =F34/F28 -> 0.015575523 | H14: =G34/G28 -> 0.0437748 | I14: =H34/H28 -> 0.053541115 | J14: =J34/I28 -> 0.096972766
C15: Tax Rate (% of Earnings Before Tax) | E15: =E39/E37 -> 0.0012357196 | F15: =F39/F37 -> 0.034919306 | G15: =G39/G37 -> 0.18905573 | H15: =H39/H37 -> 0.10393532 | I15: =I39/I37 -> 0.10396225 | J15: =J39/J37 -> 0.12193923
C16: Capital Expenditures ($000's)
C17: Debt Issuance (Repayment) ($000's)
C18: Equity Issued (Repaid) ($000's)
C20: Income Statement
C21: REVENUE
B22: Revenue | C22: Total Revenue | D22: =IFERROR(GETPIVOTDATA("Value",Pivot!$B2,"Metric",$B22,"Date",D$3),0) -> 190850000 | E22: =IFERROR(GETPIVOTDATA("Value",Pivot!$B2,"Metric",$B22,"Date",E$3),0) -> 249815000 | F22: =IFERROR(GETPIVOTDATA("Value",Pivot!$B2,"Metric",$B22,"Date",F$3),0) -> 823878000 | G22: =IFERROR(GETPIVOTDATA("Value",Pivot!$B2,"Metric",$B22,"Date",G$3),0) -> 1369722000 | H22: =IFERROR(GETPIVOTDATA("Value",Pivot!$B2,"Metric",$B22,"Date",H$3),0) -> 1731608000 | I22: =IFERROR(GETPIVOTDATA("Value",Pivot!$B2,"Metric",$B22,"Date",I$3),0) -> 2295427000 | J22: =IFERROR(GETPIVOTDATA("Value",Pivot!$B2,"Metric",$B22,"Date",J$3),0) -> 2870178000
C24: EXPENSES
B25: Compensation | C25: Compensation | D25: =-IFERROR(GETPIVOTDATA("Value",Pivot!$B$2,"Metric",$B25,"Date",D$3),0) -> -111773000 | E25: =-IFERROR(GETPIVOTDATA("Value",Pivot!$B$2,"Metric",$B25,"Date",E$3),0) -> -240731000 | F25: =-IFERROR(GETPIVOTDATA("Value",Pivot!$B$2,"Metric",$B25,"Date",F$3),0) -> -1496988000 | G25: =-IFERROR(GETPIVOTDATA("Value",Pivot!$B$2,"Metric",$B25,"Date",G$3),0) -> -894686000 | H25: =-IFERROR(GETPIVOTDATA("Value",Pivot!$B$2,"Metric",$B25,"Date",H$3),0) -> -870642000 | I25: =-IFERROR(GETPIVOTDATA("Value",Pivot!$B$2,"Metric",$B25,"Date",I$3),0) -> -1017483000 | J25: =-IFERROR(GETPIVOTDATA("Value",Pivot!$B$2,"Metric",$B25,"Date",J$3),0) -> -1307040000
B26: DepreciationAndAmortization | C26: Depreciation & Amortization of Intangible Assets | D26: =-IFERROR(GETPIVOTDATA("Value",Pivot!$B$2,"Metric",$B26,"Date",D$3),0) -> 0 | E26: =-IFERROR(GETPIVOTDATA("Value",Pivot!$B$2,"Metric",$B26,"Date",E$3),0) -> 0 | F26: =-IFERROR(GETPIVOTDATA("Value",Pivot!$B$2,"Metric",$B26,"Date",F$3),0) -> -113889000 | G26: =-IFERROR(GETPIVOTDATA("Value",Pivot!$B$2,"Metric",$B26,"Date",G$3),0) -> -256909000 | H26: =-IFERROR(GETPIVOTDATA("Value",Pivot!$B$2,"Metric",$B26,"Date",H$3),0) -> -300341000 | I26: =-IFERROR(GETPIVOTDATA("Value",Pivot!$B$2,"Metric",$B26,"Date",I$3),0) -> -258256000 | J26: =-IFERROR(GETPIVOTDATA("Value",Pivot!$B$2,"Metric",$B26,"Date",J$3),0) -> -358952000
B27: GeneralAndAdministrativeExpense | C27: General & Administrative | D27: =-IFERROR(GETPIVOTDATA("Value",Pivot!$B$2,"Metric",$B27,"Date",D$3),0) -> -51710000 | E27: =-IFERROR(GETPIVOTDATA("Value",Pivot!$B$2,"Metric",$B27,"Date",E$3),0) -> -67811000 | F27: =-IFERROR(GETPIVOTDATA("Value",Pivot!$B$2,"Metric",$B27,"Date",F$3),0) -> -140268000 | G27: =-IFERROR(GETPIVOTDATA("Value",Pivot!$B$2,"Metric",$B27,"Date",G$3),0) -> -220610000 | H27: =-IFERROR(GETPIVOTDATA("Value",Pivot!$B$2,"Metric",$B27,"Date",H$3),0) -> -242809000 | I27: =-IFERROR(GETPIVOTDATA("Value",Pivot!$B$2,"Metric",$B27,"Date",I$3),0) -> -412931000 | J27: =-IFERROR(GETPIVOTDATA("Value",Pivot!$B$2,"Metric",$B27,"Date",J$3),0) -> -747936000
C28: Total Operating Expenses | D28: =SUM(D25:D27) -> -163483000 | E28: =SUM(E25:E27) -> -308542000 | F28: =SUM(F25:F27) -> -1751145000 | G28: =SUM(G25:G27) -> -1372205000 | H28: =SUM(H25:H27) -> -1413792000 | I28: =SUM(I25:I27) -> -1688670000 | J28: =SUM(J25:J27) -> -2413928000
C30: Operating Income | D30: =D22+D28 -> 27367000 | E30: =E22+E28 -> -58727000 | F30: =F22+F28 -> -927267000 | G30: =G22+G28 -> -2483000 | H30: =H22+H28 -> 317816000 | I30: =I22+I28 -> 606757000 | J30: =J22+J28 -> 456250000
C32: OTHER INCOME (Expense)
B33: InterestAndDividendIncome | C33: Interest & Dividend Income | D33: =IFERROR(GETPIVOTDATA("Value",Pivot!$B$2,"Metric",$B33,"Date",D$3),0) -> 0 | E33: =IFERROR(GETPIVOTDATA("Value",Pivot!$B$2,"Metric",$B33,"Date",E$3),0) -> 0 | F33: =IFERROR(GETPIVOTDATA("Value",Pivot!$B$2,"Metric",$B33,"Date",F$3),0) -> 387000 | G33: =IFERROR(GETPIVOTDATA("Value",Pivot!$B$2,"Metric",$B33,"Date",G$3),0) -> 4357000 | H33: =IFERROR(GETPIVOTDATA("Value",Pivot!$B$2,"Metric",$B33,"Date",H$3),0) -> 22176000 | I33: =IFERROR(GETPIVOTDATA("Value",Pivot!$B$2,"Metric",$B33,"Date",I$3),0) -> 42172000 | J33: =IFERROR(GETPIVOTDATA("Value",Pivot!$B$2,"Metric",$B33,"Date",J$3),0) -> 45184000
B34: InterestExpense | C34: Interest Expense | D34: =-IFERROR(GETPIVOTDATA("Value",Pivot!$B$2,"Metric",$B34,"Date",D$3),0) -> -6662000 | E34: =-IFERROR(GETPIVOTDATA("Value",Pivot!$B$2,"Metric",$B34,"Date",E$3),0) -> -23816000 | F34: =-IFERROR(GETPIVOTDATA("Value",Pivot!$B$2,"Metric",$B34,"Date",F$3),0) -> -27275000 | G34: -60068000 | H34: =-IFERROR(GETPIVOTDATA("Value",Pivot!$B$2,"Metric",$B34,"Date",H$3),0) -> -75696000 | I34: -121894000 | J34: -163755000 | K34: 2022 SEC tag captures $55,711K; remaining $4,357K tagged separately per 10-K. | O34: : InterestExpenseNonoperating
B35: GainLossOnInvestments | C35: Net Gains (Losses) on Investments | D35: =IFERROR(GETPIVOTDATA("Value",Pivot!$B$2,"Metric",$B35,"Date",D$3),0) -> 0 | E35: =IFERROR(GETPIVOTDATA("Value",Pivot!$B$2,"Metric",$B35,"Date",E$3),0) -> 0 | F35: =IFERROR(GETPIVOTDATA("Value",Pivot!$B$2,"Metric",$B35,"Date",F$3),0) -> -3526000 | G35: =IFERROR(GETPIVOTDATA("Value",Pivot!$B$2,"Metric",$B35,"Date",G$3),0) -> -132000 | H35: =IFERROR(GETPIVOTDATA("Value",Pivot!$B$2,"Metric",$B35,"Date",H$3),0) -> 4203000 | I35: =IFERROR(GETPIVOTDATA("Value",Pivot!$B$2,"Metric",$B35,"Date",I$3),0) -> 1713000 | J35: =IFERROR(GETPIVOTDATA("Value",Pivot!$B$2,"Metric",$B35,"Date",J$3),0) -> -7105000
B36: Hardcoded | C36: Other Items | D36: 0 | E36: 0 | F36: -909796000 | G36: 8711000 | H36: -22115000 | I36: -59520000 | J36: 17337000
C37: Pre-Tax Income | D37: =D30+D33+D34+D35+D36 -> 20705000 | E37: =E30+E33+E34+E35+E36 -> -82543000 | F37: =F30+F33+F34+F35+F36 -> -1867477000 | G37: =G30+G33+G34+G35+G36 -> -49615000 | H37: =H30+H33+H34+H35+H36 -> 246384000 | I37: =I30+I33+I34+I35+I36 -> 469228000 | J37: =J30+J33+J34+J35+J36 -> 347911000 | L37: =F37+1867477000 -> 0
B39: IncomeTaxExpense | C39: Income Taxes | D39: =IFERROR(GETPIVOTDATA("Value",Pivot!$B$2,"Metric",$B39,"Date",D$3),0) -> 240000 | E39: =IFERROR(GETPIVOTDATA("Value",Pivot!$B$2,"Metric",$B39,"Date",E$3),0) -> -102000 | F39: =IFERROR(GETPIVOTDATA("Value",Pivot!$B$2,"Metric",$B39,"Date",F$3),0) -> -65211000 | G39: =IFERROR(GETPIVOTDATA("Value",Pivot!$B$2,"Metric",$B39,"Date",G$3),0) -> -9380000 | H39: =IFERROR(GETPIVOTDATA("Value",Pivot!$B$2,"Metric",$B39,"Date",H$3),0) -> 25608000 | I39: =IFERROR(GETPIVOTDATA("Value",Pivot!$B$2,"Metric",$B39,"Date",I$3),0) -> 48782000 | J39: =IFERROR(GETPIVOTDATA("Value",Pivot!$B$2,"Metric",$B39,"Date",J$3),0) -> 42424000
B41: consolidatedNetIncome | C41: Consolidated Net Income | D41: =IFERROR(GETPIVOTDATA("Value",Pivot!$B$2,"Metric",$B41,"Date",D$3),0) -> 20465000 | E41: =IFERROR(GETPIVOTDATA("Value",Pivot!$B$2,"Metric",$B41,"Date",E$3),0) -> -82441000 | F41: =IFERROR(GETPIVOTDATA("Value",Pivot!$B$2,"Metric",$B41,"Date",F$3),0) -> -1802266000 | G41: =IFERROR(GETPIVOTDATA("Value",Pivot!$B$2,"Metric",$B41,"Date",G$3),0) -> -40235000 | H41: =IFERROR(GETPIVOTDATA("Value",Pivot!$B$2,"Metric",$B41,"Date",H$3),0) -> 220776000 | I41: =IFERROR(GETPIVOTDATA("Value",Pivot!$B$2,"Metric",$B41,"Date",I$3),0) -> 420446000 | J41: =IFERROR(GETPIVOTDATA("Value",Pivot!$B$2,"Metric",$B41,"Date",J$3),0) -> 305487000
B42: Hardcoded | C42: (- ) NCI :Net income attributable to noncontrolling interests | D42: =IFERROR(GETPIVOTDATA("Value",Pivot!$B$2,"Metric",$B42,"Date",D$3),0) -> 0 | E42: 4610000 | F42: 1426095000 | G42: 30946000 | H42: -166433000 | I42: -310862000 | J42: -226654000
B43: NetIncomeLoss | C43: Net Income to Blue Owl | D43: =IFERROR(GETPIVOTDATA("Value",Pivot!$B$2,"Metric",$B43,"Date",D$3),0) -> 22958000 | E43: =E41+E42 -> -77831000 | F43: =F41+F42 -> -376171000 | G43: =G41+G42 -> -9289000 | H43: =H41+H42 -> 54343000 | I43: =I41+I42 -> 109584000 | J43: =J41+J42 -> 78833000
C45: EBITDA | D45: =D30+D26 -> 27367000 | E45: =E30+E26 -> -58727000 | F45: =F30-F26 -> -813378000 | G45: =G30-G26 -> 254426000 | H45: =H30-H26 -> 618157000 | I45: =I30-I26 -> 865013000 | J45: =J30-J26 -> 815202000
C47: Balance Sheet
C48: ASSETS
B49: Cash | C49: Cash | D49: =IFERROR(GETPIVOTDATA("Value",Pivot!$B$2,"Metric", $B49,"Date",D$3),0) -> 0 | E49: =IFERROR(GETPIVOTDATA("Value",Pivot!$B$2,"Metric", $B49,"Date",E$3),0) -> 11630000 | F49: =IFERROR(GETPIVOTDATA("Value",Pivot!$B$2,"Metric", $B49,"Date",F$3),0) -> 42567000 | G49: =IFERROR(GETPIVOTDATA("Value",Pivot!$B$2,"Metric", $B49,"Date",G$3),0) -> 68079000 | H49: =IFERROR(GETPIVOTDATA("Value",Pivot!$B$2,"Metric", $B49,"Date",H$3),0) -> 104160000 | I49: =IFERROR(GETPIVOTDATA("Value",Pivot!$B$2,"Metric", $B49,"Date",I$3),0) -> 152089000 | J49: =IFERROR(GETPIVOTDATA("Value",Pivot!$B$2,"Metric", $B49,"Date",J$3),0) -> 194512000
B50: DueFromRelatedParties | C50: Due from Related Parties | D50: =IFERROR(GETPIVOTDATA("Value",Pivot!$B$2,"Metric", $B50,"Date",D$3),0) -> 0 | E50: =IFERROR(GETPIVOTDATA("Value",Pivot!$B$2,"Metric", $B50,"Date",E$3),0) -> 92698000 | F50: =IFERROR(GETPIVOTDATA("Value",Pivot!$B$2,"Metric", $B50,"Date",F$3),0) -> 224576000 | G50: =IFERROR(GETPIVOTDATA("Value",Pivot!$B$2,"Metric", $B50,"Date",G$3),0) -> 357921000 | H50: 367136000 | I50: 548730000 | J50: 694056000
B51: Investments | C51: Investments | D51: =IFERROR(GETPIVOTDATA("Value",Pivot!$B$2,"Metric", $B51,"Date",D$3),0) -> 0 | E51: =IFERROR(GETPIVOTDATA("Value",Pivot!$B$2,"Metric", $B51,"Date",E$3),0) -> 2678000 | F51: =IFERROR(GETPIVOTDATA("Value",Pivot!$B$2,"Metric", $B51,"Date",F$3),0) -> 12143000 | G51: =IFERROR(GETPIVOTDATA("Value",Pivot!$B$2,"Metric", $B51,"Date",G$3),0) -> 317231000 | H51: =IFERROR(GETPIVOTDATA("Value",Pivot!$B$2,"Metric", $B51,"Date",H$3),0) -> 344265000 | I51: =IFERROR(GETPIVOTDATA("Value",Pivot!$B$2,"Metric", $B51,"Date",I$3),0) -> 486945000 | J51: =IFERROR(GETPIVOTDATA("Value",Pivot!$B$2,"Metric", $B51,"Date",J$3),0) -> 484389000
B52: OperatingLeaseRightOfUseAsset | C52: Operating Lease Assets | D52: =IFERROR(GETPIVOTDATA("Value",Pivot!$B$2,"Metric", $B52,"Date",D$3),0) -> 0 | E52: =IFERROR(GETPIVOTDATA("Value",Pivot!$B$2,"Metric", $B52,"Date",E$3),0) -> 0 | F52: =IFERROR(GETPIVOTDATA("Value",Pivot!$B$2,"Metric", $B52,"Date",F$3),0) -> 86033000 | G52: =IFERROR(GETPIVOTDATA("Value",Pivot!$B$2,"Metric", $B52,"Date",G$3),0) -> 224411000 | H52: =IFERROR(GETPIVOTDATA("Value",Pivot!$B$2,"Metric", $B52,"Date",H$3),0) -> 281669000 | I52: =IFERROR(GETPIVOTDATA("Value",Pivot!$B$2,"Metric", $B52,"Date",I$3),0) -> 325090000 | J52: =IFERROR(GETPIVOTDATA("Value",Pivot!$B$2,"Metric", $B52,"Date",J$3),0) -> 456204000
B53: IntangibleAssetsNet | C53: Intangible Assets (Net) | D53: =IFERROR(GETPIVOTDATA("Value",Pivot!$B$2,"Metric", $B53,"Date",D$3),0) -> 0 | E53: =IFERROR(GETPIVOTDATA("Value",Pivot!$B$2,"Metric", $B53,"Date",E$3),0) -> 0 | F53: =IFERROR(GETPIVOTDATA("Value",Pivot!$B$2,"Metric", $B53,"Date",F$3),0) -> 2611411000 | G53: =IFERROR(GETPIVOTDATA("Value",Pivot!$B$2,"Metric", $B53,"Date",G$3),0) -> 2405422000 | H53: =IFERROR(GETPIVOTDATA("Value",Pivot!$B$2,"Metric", $B53,"Date",H$3),0) -> 2110008000 | I53: =IFERROR(GETPIVOTDATA("Value",Pivot!$B$2,"Metric", $B53,"Date",I$3),0) -> 2902752000 | J53: =IFERROR(GETPIVOTDATA("Value",Pivot!$B$2,"Metric", $B53,"Date",J$3),0) -> 2888800000
B54: PPENet | C54: PPE Net | D54: =IFERROR(GETPIVOTDATA("Value",Pivot!$B$2,"Metric", $B54,"Date",D$3),0) -> 0 | E54: =IFERROR(GETPIVOTDATA("Value",Pivot!$B$2,"Metric", $B54,"Date",E$3),0) -> 3356000 | F54: =IFERROR(GETPIVOTDATA("Value",Pivot!$B$2,"Metric", $B54,"Date",F$3),0) -> 7951000 | G54: =IFERROR(GETPIVOTDATA("Value",Pivot!$B$2,"Metric", $B54,"Date",G$3),0) -> 71190000 | H54: =IFERROR(GETPIVOTDATA("Value",Pivot!$B$2,"Metric", $B54,"Date",H$3),0) -> 134893000 | I54: =IFERROR(GETPIVOTDATA("Value",Pivot!$B$2,"Metric", $B54,"Date",I$3),0) -> 187749000 | J54: =IFERROR(GETPIVOTDATA("Value",Pivot!$B$2,"Metric", $B54,"Date",J$3),0) -> 218941000
B55: Goodwill | C55: Goodwill | D55: =IFERROR(GETPIVOTDATA("Value",Pivot!$B$2,"Metric", $B55,"Date",D$3),0) -> 0 | E55: =IFERROR(GETPIVOTDATA("Value",Pivot!$B$2,"Metric", $B55,"Date",E$3),0) -> 0 | F55: =IFERROR(GETPIVOTDATA("Value",Pivot!$B$2,"Metric", $B55,"Date",F$3),0) -> 4132245000 | G55: =IFERROR(GETPIVOTDATA("Value",Pivot!$B$2,"Metric", $B55,"Date",G$3),0) -> 4205159000 | H55: =IFERROR(GETPIVOTDATA("Value",Pivot!$B$2,"Metric", $B55,"Date",H$3),0) -> 4224153000 | I55: =IFERROR(GETPIVOTDATA("Value",Pivot!$B$2,"Metric", $B55,"Date",I$3),0) -> 4699465000 | J55: =IFERROR(GETPIVOTDATA("Value",Pivot!$B$2,"Metric", $B55,"Date",J$3),0) -> 5624469000
B56: OtherAssets | C56: Other Assets | D56: =IFERROR(GETPIVOTDATA("Value",Pivot!$B$2,"Metric", $B56,"Date",D$3),0) -> 0 | E56: =IFERROR(GETPIVOTDATA("Value",Pivot!$B$2,"Metric", $B56,"Date",E$3),0) -> 16469000 | F56: =IFERROR(GETPIVOTDATA("Value",Pivot!$B$2,"Metric", $B56,"Date",F$3),0) -> 38620000 | G56: =IFERROR(GETPIVOTDATA("Value",Pivot!$B$2,"Metric", $B56,"Date",G$3),0) -> 99679000 | H56: =IFERROR(GETPIVOTDATA("Value",Pivot!$B$2,"Metric", $B56,"Date",H$3),0) -> 187455000 | I56: =IFERROR(GETPIVOTDATA("Value",Pivot!$B$2,"Metric", $B56,"Date",I$3),0) -> 258748000 | J56: =IFERROR(GETPIVOTDATA("Value",Pivot!$B$2,"Metric", $B56,"Date",J$3),0) -> 382519000
C57: Unidentified Assets | D57: =D58-SUM(D49:D56) -> 0 | E57: =E58-SUM(E49:E56) -> 149485182 | F57: =F58-SUM(F49:F56) -> 1110852000 | G57: =G58-SUM(G49:G56) -> 1143983000 | H57: =H58-SUM(H49:H56) -> 1063882000 | I57: =I58-SUM(I49:I56) -> 1430902000 | J57: =J58-SUM(J49:J56) -> 1523794000
B58: Assets | C58: Total Assets | D58: =IFERROR(GETPIVOTDATA("Value",Pivot!$B$2,"Metric", $B58,"Date",D$3),0) -> 0 | E58: =IFERROR(GETPIVOTDATA("Value",Pivot!$B$2,"Metric", $B58,"Date",E$3),0) -> 276316182 | F58: =IFERROR(GETPIVOTDATA("Value",Pivot!$B$2,"Metric", $B58,"Date",F$3),0) -> 8266398000 | G58: =IFERROR(GETPIVOTDATA("Value",Pivot!$B$2,"Metric", $B58,"Date",G$3),0) -> 8893075000 | H58: =IFERROR(GETPIVOTDATA("Value",Pivot!$B$2,"Metric", $B58,"Date",H$3),0) -> 8817621000 | I58: =IFERROR(GETPIVOTDATA("Value",Pivot!$B$2,"Metric", $B58,"Date",I$3),0) -> 10992470000 | J58: =IFERROR(GETPIVOTDATA("Value",Pivot!$B$2,"Metric", $B58,"Date",J$3),0) -> 12467684000
C60: LIABILITIES
B61: LongTermDebt | C61: Long Term Debt | D61: =IFERROR(GETPIVOTDATA("Value",Pivot!$B$2,"Metric", $B61,"Date",D$3),0) -> 0 | E61: =IFERROR(GETPIVOTDATA("Value",Pivot!$B$2,"Metric", $B61,"Date",E$3),0) -> 356386000 | F61: =IFERROR(GETPIVOTDATA("Value",Pivot!$B$2,"Metric", $B61,"Date",F$3),0) -> 1174167000 | G61: =IFERROR(GETPIVOTDATA("Value",Pivot!$B$2,"Metric", $B61,"Date",G$3),0) -> 1624771000 | H61: =IFERROR(GETPIVOTDATA("Value",Pivot!$B$2,"Metric", $B61,"Date",H$3),0) -> 1681241000 | I61: =IFERROR(GETPIVOTDATA("Value",Pivot!$B$2,"Metric", $B61,"Date",I$3),0) -> 2588496000 | J61: =IFERROR(GETPIVOTDATA("Value",Pivot!$B$2,"Metric", $B61,"Date",J$3),0) -> 3324426000
B62: AccruedCompensation | C62: Accrued Compensation | D62: =IFERROR(GETPIVOTDATA("Value",Pivot!$B$2,"Metric", $B62,"Date",D$3),0) -> 0 | E62: =IFERROR(GETPIVOTDATA("Value",Pivot!$B$2,"Metric", $B62,"Date",E$3),0) -> 207957000 | F62: =IFERROR(GETPIVOTDATA("Value",Pivot!$B$2,"Metric", $B62,"Date",F$3),0) -> 155606000 | G62: =IFERROR(GETPIVOTDATA("Value",Pivot!$B$2,"Metric", $B62,"Date",G$3),0) -> 309644000 | H62: =IFERROR(GETPIVOTDATA("Value",Pivot!$B$2,"Metric", $B62,"Date",H$3),0) -> 370726000 | I62: =IFERROR(GETPIVOTDATA("Value",Pivot!$B$2,"Metric", $B62,"Date",I$3),0) -> 424024000 | J62: =IFERROR(GETPIVOTDATA("Value",Pivot!$B$2,"Metric", $B62,"Date",J$3),0) -> 525550000
B63: OperatingLeaseLiability | C63: Op. Lease Liabilities | D63: =IFERROR(GETPIVOTDATA("Value",Pivot!$B$2,"Metric", $B63,"Date",D$3),0) -> 0 | E63: =IFERROR(GETPIVOTDATA("Value",Pivot!$B$2,"Metric", $B63,"Date",E$3),0) -> 0 | F63: =IFERROR(GETPIVOTDATA("Value",Pivot!$B$2,"Metric", $B63,"Date",F$3),0) -> 88480000 | G63: =IFERROR(GETPIVOTDATA("Value",Pivot!$B$2,"Metric", $B63,"Date",G$3),0) -> 239844000 | H63: =IFERROR(GETPIVOTDATA("Value",Pivot!$B$2,"Metric", $B63,"Date",H$3),0) -> 319532000 | I63: =IFERROR(GETPIVOTDATA("Value",Pivot!$B$2,"Metric", $B63,"Date",I$3),0) -> 390353000 | J63: =IFERROR(GETPIVOTDATA("Value",Pivot!$B$2,"Metric", $B63,"Date",J$3),0) -> 538147000
B64: AccountsPayableAndOther | C64: Accounts Payable | D64: =IFERROR(GETPIVOTDATA("Value",Pivot!$B$2,"Metric", $B64,"Date",D$3),0) -> 0 | E64: =IFERROR(GETPIVOTDATA("Value",Pivot!$B$2,"Metric", $B64,"Date",E$3),0) -> 58415000 | F64: =IFERROR(GETPIVOTDATA("Value",Pivot!$B$2,"Metric", $B64,"Date",F$3),0) -> 68339000 | G64: =IFERROR(GETPIVOTDATA("Value",Pivot!$B$2,"Metric", $B64,"Date",G$3),0) -> 126559000 | H64: =IFERROR(GETPIVOTDATA("Value",Pivot!$B$2,"Metric", $B64,"Date",H$3),0) -> 138754000 | I64: =IFERROR(GETPIVOTDATA("Value",Pivot!$B$2,"Metric", $B64,"Date",I$3),0) -> 165953000 | J64: =IFERROR(GETPIVOTDATA("Value",Pivot!$B$2,"Metric", $B64,"Date",J$3),0) -> 163000000
B65: DeferredTaxLiabilities | C65: Deferred Tax Liabilities | D65: =IFERROR(GETPIVOTDATA("Value",Pivot!$B$2,"Metric", $B65,"Date",D$3),0) -> 0 | E65: =IFERROR(GETPIVOTDATA("Value",Pivot!$B$2,"Metric", $B65,"Date",E$3),0) -> 0 | F65: =IFERROR(GETPIVOTDATA("Value",Pivot!$B$2,"Metric", $B65,"Date",F$3),0) -> 48962000 | G65: =IFERROR(GETPIVOTDATA("Value",Pivot!$B$2,"Metric", $B65,"Date",G$3),0) -> 41791000 | H65: =IFERROR(GETPIVOTDATA("Value",Pivot!$B$2,"Metric", $B65,"Date",H$3),0) -> 34419000 | I65: =IFERROR(GETPIVOTDATA("Value",Pivot!$B$2,"Metric", $B65,"Date",I$3),0) -> 36867000 | J65: =IFERROR(GETPIVOTDATA("Value",Pivot!$B$2,"Metric", $B65,"Date",J$3),0) -> 39663000
C66: Other Liabilities | D66: =D67-(D61+D62+D64+D65) -> 0 | E66: =E67-(E61+E62+E64+E65) -> -612990899 | F66: =F67-(F61+F62+F64+F65) -> 971754000 | G66: =G67-(G61+G62+G64+G65) -> 1241424000 | H66: =H67-(H61+H62+H64+H65) -> 1314550000 | I66: =I67-(I61+I62+I64+I65) -> 1971094000 | J66: =J67-(J61+J62+J64+J65) -> 2360846000
B67: Liabilities | C67: Total Liabilities | D67: =IFERROR(GETPIVOTDATA("Value",Pivot!$B$2,"Metric", $B67,"Date",D$3),0) -> 0 | E67: =IFERROR(GETPIVOTDATA("Value",Pivot!$B$2,"Metric", $B67,"Date",E$3),0) -> 9767101 | F67: =IFERROR(GETPIVOTDATA("Value",Pivot!$B$2,"Metric", $B67,"Date",F$3),0) -> 2418828000 | G67: =IFERROR(GETPIVOTDATA("Value",Pivot!$B$2,"Metric", $B67,"Date",G$3),0) -> 3344189000 | H67: =IFERROR(GETPIVOTDATA("Value",Pivot!$B$2,"Metric", $B67,"Date",H$3),0) -> 3539690000 | I67: =IFERROR(GETPIVOTDATA("Value",Pivot!$B$2,"Metric", $B67,"Date",I$3),0) -> 5186434000 | J67: =IFERROR(GETPIVOTDATA("Value",Pivot!$B$2,"Metric", $B67,"Date",J$3),0) -> 6413485000
C69: SHAREHOLDERS EQUITY
B70: AdditionalPaidInCapital | C70: Additional Paid-in Capital | D70: =IFERROR(GETPIVOTDATA("Value",Pivot!$B$2,"Metric", $B70,"Date",D$3),0) -> 0 | E70: =IFERROR(GETPIVOTDATA("Value",Pivot!$B$2,"Metric", $B70,"Date",E$3),0) -> 5260809 | F70: =IFERROR(GETPIVOTDATA("Value",Pivot!$B$2,"Metric", $B70,"Date",F$3),0) -> 2160934000 | G70: =IFERROR(GETPIVOTDATA("Value",Pivot!$B$2,"Metric", $B70,"Date",G$3),0) -> 2293903000 | H70: =IFERROR(GETPIVOTDATA("Value",Pivot!$B$2,"Metric", $B70,"Date",H$3),0) -> 2410982000 | I70: =IFERROR(GETPIVOTDATA("Value",Pivot!$B$2,"Metric", $B70,"Date",I$3),0) -> 3269239000 | J70: =IFERROR(GETPIVOTDATA("Value",Pivot!$B$2,"Metric", $B70,"Date",J$3),0) -> 3812770000
B71: AccumulatedDeficit | C71: Accumulated Deficit (RE) | D71: =IFERROR(GETPIVOTDATA("Value",Pivot!$B$2,"Metric", $B71,"Date",D$3),0) -> 0 | E71: =IFERROR(GETPIVOTDATA("Value",Pivot!$B$2,"Metric", $B71,"Date",E$3),0) -> -261631 | F71: =IFERROR(GETPIVOTDATA("Value",Pivot!$B$2,"Metric", $B71,"Date",F$3),0) -> -497506000 | G71: =IFERROR(GETPIVOTDATA("Value",Pivot!$B$2,"Metric", $B71,"Date",G$3),0) -> -689345000 | H71: =IFERROR(GETPIVOTDATA("Value",Pivot!$B$2,"Metric", $B71,"Date",H$3),0) -> -882884000 | I71: =IFERROR(GETPIVOTDATA("Value",Pivot!$B$2,"Metric", $B71,"Date",I$3),0) -> -1141631000 | J71: =IFERROR(GETPIVOTDATA("Value",Pivot!$B$2,"Metric", $B71,"Date",J$3),0) -> -1609455000
B72: StockholdersEquity | C72: Total Shareholders’Equity - Blue Owl | D72: =IFERROR(GETPIVOTDATA("Value",Pivot!$B$2,"Metric", $B72,"Date",D$3),0) -> 0 | E72: =IFERROR(GETPIVOTDATA("Value",Pivot!$B$2,"Metric", $B72,"Date",E$3),0) -> 5000001 | F72: =IFERROR(GETPIVOTDATA("Value",Pivot!$B$2,"Metric", $B72,"Date",F$3),0) -> 1663567000 | G72: =IFERROR(GETPIVOTDATA("Value",Pivot!$B$2,"Metric", $B72,"Date",G$3),0) -> 1604698000 | H72: =IFERROR(GETPIVOTDATA("Value",Pivot!$B$2,"Metric", $B72,"Date",H$3),0) -> 1528239000 | I72: =IFERROR(GETPIVOTDATA("Value",Pivot!$B$2,"Metric", $B72,"Date",I$3),0) -> 2127758000 | J72: =IFERROR(GETPIVOTDATA("Value",Pivot!$B$2,"Metric", $B72,"Date",J$3),0) -> 2205362000
B73: MinorityInterest | C73: Noncontrolling Interest | D73: =IFERROR(GETPIVOTDATA("Value",Pivot!$B$2,"Metric", $B73,"Date",D$3),0) -> 0 | E73: =IFERROR(GETPIVOTDATA("Value",Pivot!$B$2,"Metric", $B73,"Date",E$3),0) -> 6526000 | F73: =IFERROR(GETPIVOTDATA("Value",Pivot!$B$2,"Metric", $B73,"Date",F$3),0) -> 4184003000 | G73: =IFERROR(GETPIVOTDATA("Value",Pivot!$B$2,"Metric", $B73,"Date",G$3),0) -> 3944188000 | H73: =IFERROR(GETPIVOTDATA("Value",Pivot!$B$2,"Metric", $B73,"Date",H$3),0) -> 3749692000 | I73: =IFERROR(GETPIVOTDATA("Value",Pivot!$B$2,"Metric", $B73,"Date",I$3),0) -> 3678278000 | J73: =IFERROR(GETPIVOTDATA("Value",Pivot!$B$2,"Metric", $B73,"Date",J$3),0) -> 3848837000
C74: Total Equity | D74: =D72+D73 -> 0 | E74: =E72+E73 -> 11526001 | F74: =F72+F73 -> 5847570000 | G74: =G72+G73 -> 5548886000 | H74: =H72+H73 -> 5277931000 | I74: =I72+I73 -> 5806036000 | J74: =J72+J73 -> 6054199000
C76: Total Liabilities & Shareholder's Equity | D76: =SUM(D74,D67) -> 0 | E76: =E74+E67 -> 21293102 | F76: =F74+F67 -> 8266398000 | G76: =G74+G67 -> 8893075000 | H76: =H74+H67 -> 8817621000 | I76: =I74+I67 -> 10992470000 | J76: =J74+J67 -> 12467684000
C78: Check | E78: =E58-E76 -> 255023080 | F78: =F58-F76 -> 0 | G78: =G58-G76 -> 0 | H78: =H58-H76 -> 0 | I78: =I58-I76 -> 0 | J78: =J58-J76 -> 0
E79: 2020: SPAC transition year — balance sheet incomplete
C80: Cash Flow Statement
C82: Operating Cash Flow
B83: ConsolidatedNetIncome | C83: Consolidated Net Income (Loss) | D83: =IFERROR(GETPIVOTDATA("Value",Pivot!$B$2,"Metric", $B83,"Date",D$3),0) -> 20465000 | E83: =IFERROR(GETPIVOTDATA("Value",Pivot!$B$2,"Metric", $B83,"Date",E$3),0) -> -82441000 | F83: =IFERROR(GETPIVOTDATA("Value",Pivot!$B$2,"Metric", $B83,"Date",F$3),0) -> -1802266000 | G83: =IFERROR(GETPIVOTDATA("Value",Pivot!$B$2,"Metric", $B83,"Date",G$3),0) -> -40235000 | H83: =IFERROR(GETPIVOTDATA("Value",Pivot!$B$2,"Metric", $B83,"Date",H$3),0) -> 220776000 | I83: =IFERROR(GETPIVOTDATA("Value",Pivot!$B$2,"Metric", $B83,"Date",I$3),0) -> 420446000 | J83: =IFERROR(GETPIVOTDATA("Value",Pivot!$B$2,"Metric", $B83,"Date",J$3),0) -> 305487000
B84: Depreciation | C84: Depreciation of Fixed Assets | D84: =IFERROR(GETPIVOTDATA("Value",Pivot!$B$2,"Metric", $B84,"Date",D$3),0) -> 829000 | E84: =IFERROR(GETPIVOTDATA("Value",Pivot!$B$2,"Metric", $B84,"Date",E$3),0) -> 673000 | F84: =IFERROR(GETPIVOTDATA("Value",Pivot!$B$2,"Metric", $B84,"Date",F$3),0) -> 665000 | G84: =IFERROR(GETPIVOTDATA("Value",Pivot!$B$2,"Metric", $B84,"Date",G$3),0) -> 2304000 | H84: =IFERROR(GETPIVOTDATA("Value",Pivot!$B$2,"Metric", $B84,"Date",H$3),0) -> 10226000 | I84: =IFERROR(GETPIVOTDATA("Value",Pivot!$B$2,"Metric", $B84,"Date",I$3),0) -> 16660000 | J84: =IFERROR(GETPIVOTDATA("Value",Pivot!$B$2,"Metric", $B84,"Date",J$3),0) -> 23446000
C85: (+) Depreciation & Amortization | D85: =ABS(D26) -> 0 | E85: =ABS(E26) -> 0 | F85: =ABS(F26) -> 113889000 | G85: =ABS(G26) -> 256909000 | H85: =ABS(H26) -> 300341000 | I85: =ABS(I26) -> 258256000 | J85: =ABS(J26) -> 358952000
B86: ShareBasedCompensation | C86: (+) Equity-Based Compensation | D86: =IFERROR(GETPIVOTDATA("Value",Pivot!$B$2,"Metric", $B86,"Date",D$3),0) -> 0 | E86: =IFERROR(GETPIVOTDATA("Value",Pivot!$B$2,"Metric", $B86,"Date",E$3),0) -> 0 | F86: =IFERROR(GETPIVOTDATA("Value",Pivot!$B$2,"Metric", $B86,"Date",F$3),0) -> 1205336000 | G86: =IFERROR(GETPIVOTDATA("Value",Pivot!$B$2,"Metric", $B86,"Date",G$3),0) -> 420832000 | H86: =IFERROR(GETPIVOTDATA("Value",Pivot!$B$2,"Metric", $B86,"Date",H$3),0) -> 312564000 | I86: =IFERROR(GETPIVOTDATA("Value",Pivot!$B$2,"Metric", $B86,"Date",I$3),0) -> 312609000 | J86: =IFERROR(GETPIVOTDATA("Value",Pivot!$B$2,"Metric", $B86,"Date",J$3),0) -> 673524000
C87: Other Non-Cash & WC Changes | D87: =D88-D83-D84-D85-D86 -> 22770000 | E87: =E88-E83-E84-E85-E86 -> 87002000 | F87: =F88-F83-F84-F85-F86 -> 764034000 | G87: =G88-G83-G84-G85-G86 -> 88637000 | H87: =H88-H83-H84-H85-H86 -> 105238000 | I87: =I88-I83-I84-I85-I86 -> -8416000 | J87: =J88-J83-J84-J85-J86 -> -105377000
B88: OperatingCashFlow | C88: Cash from Operations | D88: =IFERROR(GETPIVOTDATA("Value",Pivot!$B$2,"Metric", $B88,"Date",D$3),0) -> 44064000 | E88: =IFERROR(GETPIVOTDATA("Value",Pivot!$B$2,"Metric", $B88,"Date",E$3),0) -> 5234000 | F88: =IFERROR(GETPIVOTDATA("Value",Pivot!$B$2,"Metric", $B88,"Date",F$3),0) -> 281658000 | G88: =IFERROR(GETPIVOTDATA("Value",Pivot!$B$2,"Metric", $B88,"Date",G$3),0) -> 728447000 | H88: =IFERROR(GETPIVOTDATA("Value",Pivot!$B$2,"Metric", $B88,"Date",H$3),0) -> 949145000 | I88: =IFERROR(GETPIVOTDATA("Value",Pivot!$B$2,"Metric", $B88,"Date",I$3),0) -> 999555000 | J88: =IFERROR(GETPIVOTDATA("Value",Pivot!$B$2,"Metric", $B88,"Date",J$3),0) -> 1256032000
C90: Investing Cash Flow
B91: CapEx | C91: CapEx | D91: =-IFERROR(GETPIVOTDATA("Value",Pivot!$B$2,"Metric", $B91,"Date",D$3),0) -> -1173000 | E91: =-IFERROR(GETPIVOTDATA("Value",Pivot!$B$2,"Metric", $B91,"Date",E$3),0) -> -652000 | F91: =-IFERROR(GETPIVOTDATA("Value",Pivot!$B$2,"Metric", $B91,"Date",F$3),0) -> -5261000 | G91: =-IFERROR(GETPIVOTDATA("Value",Pivot!$B$2,"Metric", $B91,"Date",G$3),0) -> -65539000 | H91: =-IFERROR(GETPIVOTDATA("Value",Pivot!$B$2,"Metric", $B91,"Date",H$3),0) -> -67905000 | I91: =-IFERROR(GETPIVOTDATA("Value",Pivot!$B$2,"Metric", $B91,"Date",I$3),0) -> -64187000 | J91: =-IFERROR(GETPIVOTDATA("Value",Pivot!$B$2,"Metric", $B91,"Date",J$3),0) -> -57748000
B92: AcquisitionPayments | C92: Cash Consideration for Acquisitions | D92: =-IFERROR(GETPIVOTDATA("Value",Pivot!$B$2,"Metric", $B92,"Date",D$3),0) -> 0 | E92: =-IFERROR(GETPIVOTDATA("Value",Pivot!$B$2,"Metric", $B92,"Date",E$3),0) -> 0 | F92: =-IFERROR(GETPIVOTDATA("Value",Pivot!$B$2,"Metric", $B92,"Date",F$3),0) -> -1578866000 | G92: =-IFERROR(GETPIVOTDATA("Value",Pivot!$B$2,"Metric", $B92,"Date",G$3),0) -> -114454000 | H92: =-IFERROR(GETPIVOTDATA("Value",Pivot!$B$2,"Metric", $B92,"Date",H$3),0) -> -26265000 | I92: =-IFERROR(GETPIVOTDATA("Value",Pivot!$B$2,"Metric", $B92,"Date",I$3),0) -> -445210000 | J92: =-IFERROR(GETPIVOTDATA("Value",Pivot!$B$2,"Metric", $B92,"Date",J$3),0) -> -244580000
C93: Other Investing Items | D93: =D94-(D92+D91) -> 0 | E93: =E94-(E92+E91) -> 0 | F93: =F94-(F92+F91) -> -14745000 | G93: =G94-(G92+G91) -> -305225000 | H93: =H94-(H92+H91) -> -23861000 | I93: =I94-(I92+I91) -> -128748000 | J93: =J94-(J92+J91) -> 31757000
B94: InvestingCashFlow | C94: Cash from Investing | D94: =IFERROR(GETPIVOTDATA("Value",Pivot!$B$2,"Metric", $B94,"Date",D$3),0) -> -1173000 | E94: =IFERROR(GETPIVOTDATA("Value",Pivot!$B$2,"Metric", $B94,"Date",E$3),0) -> -652000 | F94: =IFERROR(GETPIVOTDATA("Value",Pivot!$B$2,"Metric", $B94,"Date",F$3),0) -> -1598872000 | G94: =IFERROR(GETPIVOTDATA("Value",Pivot!$B$2,"Metric", $B94,"Date",G$3),0) -> -485218000 | H94: =IFERROR(GETPIVOTDATA("Value",Pivot!$B$2,"Metric", $B94,"Date",H$3),0) -> -118031000 | I94: =IFERROR(GETPIVOTDATA("Value",Pivot!$B$2,"Metric", $B94,"Date",I$3),0) -> -638145000 | J94: =IFERROR(GETPIVOTDATA("Value",Pivot!$B$2,"Metric", $B94,"Date",J$3),0) -> -270571000
C96: Financing Cash Flow
B97: ProceedsFromDebt | C97: Proceeds from Debt | D97: =IFERROR(GETPIVOTDATA("Value",Pivot!$B$2,"Metric", $B97,"Date",D$3),0) -> 344944000 | E97: =IFERROR(GETPIVOTDATA("Value",Pivot!$B$2,"Metric", $B97,"Date",E$3),0) -> 240547000 | F97: =IFERROR(GETPIVOTDATA("Value",Pivot!$B$2,"Metric", $B97,"Date",F$3),0) -> 1390296000 | G97: =IFERROR(GETPIVOTDATA("Value",Pivot!$B$2,"Metric", $B97,"Date",G$3),0) -> 775060000 | H97: =IFERROR(GETPIVOTDATA("Value",Pivot!$B$2,"Metric", $B97,"Date",H$3),0) -> 1054800000 | I97: =IFERROR(GETPIVOTDATA("Value",Pivot!$B$2,"Metric", $B97,"Date",I$3),0) -> 2170000000 | J97: =IFERROR(GETPIVOTDATA("Value",Pivot!$B$2,"Metric", $B97,"Date",J$3),0) -> 2270000000
B98: RepaymentsOfDebt | C98: Repayment of Debt | D98: =-IFERROR(GETPIVOTDATA("Value",Pivot!$B$2,"Metric", $B98,"Date",D$3),0) -> -83590000 | E98: =-IFERROR(GETPIVOTDATA("Value",Pivot!$B$2,"Metric", $B98,"Date",E$3),0) -> -171458000 | F98: =-IFERROR(GETPIVOTDATA("Value",Pivot!$B$2,"Metric", $B98,"Date",F$3),0) -> -577835000 | G98: =-IFERROR(GETPIVOTDATA("Value",Pivot!$B$2,"Metric", $B98,"Date",G$3),0) -> -323000000 | H98: =-IFERROR(GETPIVOTDATA("Value",Pivot!$B$2,"Metric", $B98,"Date",H$3),0) -> -1000000000 | I98: =-IFERROR(GETPIVOTDATA("Value",Pivot!$B$2,"Metric", $B98,"Date",I$3),0) -> -1245000000 | J98: =-IFERROR(GETPIVOTDATA("Value",Pivot!$B$2,"Metric", $B98,"Date",J$3),0) -> -1540000000
B99: DividendsPaid | C99: Dividends Paid | D99: =-IFERROR(GETPIVOTDATA("Value",Pivot!$B$2,"Metric", $B99,"Date",D$3),0) -> 0 | E99: =-IFERROR(GETPIVOTDATA("Value",Pivot!$B$2,"Metric", $B99,"Date",E$3),0) -> 0 | F99: =-IFERROR(GETPIVOTDATA("Value",Pivot!$B$2,"Metric", $B99,"Date",F$3),0) -> -47076000 | G99: =-IFERROR(GETPIVOTDATA("Value",Pivot!$B$2,"Metric", $B99,"Date",G$3),0) -> -182550000 | H99: =-IFERROR(GETPIVOTDATA("Value",Pivot!$B$2,"Metric", $B99,"Date",H$3),0) -> -247882000 | I99: =-IFERROR(GETPIVOTDATA("Value",Pivot!$B$2,"Metric", $B99,"Date",I$3),0) -> -368331000 | J99: =-IFERROR(GETPIVOTDATA("Value",Pivot!$B$2,"Metric", $B99,"Date",J$3),0) -> -546657000
B100: ProceedsFromEquity | C100: Issuance (repayment) of equity | D100: =IFERROR(GETPIVOTDATA("Value",Pivot!$B$2,"Metric", $B100,"Date",D$3),0) -> 0 | E100: =IFERROR(GETPIVOTDATA("Value",Pivot!$B$2,"Metric", $B100,"Date",E$3),0) -> 269500000 | F100: =IFERROR(GETPIVOTDATA("Value",Pivot!$B$2,"Metric", $B100,"Date",F$3),0) -> 0 | G100: =IFERROR(GETPIVOTDATA("Value",Pivot!$B$2,"Metric", $B100,"Date",G$3),0) -> 0 | H100: =IFERROR(GETPIVOTDATA("Value",Pivot!$B$2,"Metric", $B100,"Date",H$3),0) -> 0 | I100: =IFERROR(GETPIVOTDATA("Value",Pivot!$B$2,"Metric", $B100,"Date",I$3),0) -> 0 | J100: =IFERROR(GETPIVOTDATA("Value",Pivot!$B$2,"Metric", $B100,"Date",J$3),0) -> 0
B101: Hard coded | C101: (+) Contributions to NCI | D101: 0 | E101: 0 | F101: 15734000 | G101: 27482000 | H101: 48315000 | I101: 37897000 | J101: 29289000
B102: Hard coded | C102: (-) Distributions to NCI | D102: 0 | E102: 0 | F102: -135244000 | G102: -425164000 | H102: -546242000 | I102: -735413000 | J102: -928726000
C103: Other Financing Items | D103: =D104-(D97+D98+D99+D100+D101+D102) -> -304361000 | E103: =E104-(E97+E98+E99+E100+E101+E102) -> -338884000 | F103: =F104-(F97+F98+F99+F100+F101+F102) -> 702276000 | G103: =G104-(G97+G98+G99+G100+G101+G102) -> -89545000 | H103: =H104-(H97+H98+H99+H100+H101+H102) -> -104024000 | I103: =I104-(I97+I98+I99+I100+I101+I102) -> -172634000 | J103: =J104-(J97+J98+J99+J100+J101+J102) -> -226944000
B104: FinancingCashFlow | C104: Cash from Financing | D104: =IFERROR(GETPIVOTDATA("Value",Pivot!$B$2,"Metric", $B104,"Date",D$3),0) -> -43007000 | E104: =IFERROR(GETPIVOTDATA("Value",Pivot!$B$2,"Metric", $B104,"Date",E$3),0) -> -295000 | F104: =IFERROR(GETPIVOTDATA("Value",Pivot!$B$2,"Metric", $B104,"Date",F$3),0) -> 1348151000 | G104: =IFERROR(GETPIVOTDATA("Value",Pivot!$B$2,"Metric", $B104,"Date",G$3),0) -> -217717000 | H104: =IFERROR(GETPIVOTDATA("Value",Pivot!$B$2,"Metric", $B104,"Date",H$3),0) -> -795033000 | I104: =IFERROR(GETPIVOTDATA("Value",Pivot!$B$2,"Metric", $B104,"Date",I$3),0) -> -313481000 | J104: =IFERROR(GETPIVOTDATA("Value",Pivot!$B$2,"Metric", $B104,"Date",J$3),0) -> -943038000
C106: Net Increase (decrease) in Cash | D106: =D104+D94+D88 -> -116000 | E106: =E104+E94+E88 -> 4287000 | F106: =F104+F94+F88 -> 30937000 | G106: =G104+G94+G88 -> 25512000 | H106: =H104+H94+H88 -> 36081000 | I106: =I104+I94+I88 -> 47929000 | J106: =J104+J94+J88 -> 42423000
C107: Opening Cash Balance | E107: =D49 -> 0 | F107: =E49 -> 11630000 | G107: =F49 -> 42567000 | H107: =G49 -> 68079000 | I107: =H49 -> 104160000 | J107: =I49 -> 152089000
C108: Closing Cash Balance | D108: =D106+D107 -> -116000 | E108: =E106+E107 -> 4287000 | F108: =F106+F107 -> 42567000 | G108: =G106+G107 -> 68079000 | H108: =H106+H107 -> 104160000 | I108: =I106+I107 -> 152089000 | J108: =J106+J107 -> 194512000
C110: check | D110: =D108-D49 -> -116000 | E110: =E108-E49 -> -7343000 | F110: =F108-F49 -> 0 | G110: =G108-G49 -> 0 | H110: =H108-H49 -> 0 | I110: =I108-I49 -> 0 | J110: =J108-J49 -> 0
E111: 2020: SPAC transition year-balance sheet incomplete
C114: Share Capital (Class A/C/D) | F114: 139 | G114: 140 | H114: 141 | I114: 150 | J114: 155
C116: CREDIT RATIOS
C118: LEVERAGE
C119: Debt / EBITDA | E119: =E61/E45 -> -6.0685204 | F119: =F61/F45 -> -1.4435687 | G119: =G61/G45 -> 6.3860258 | H119: =H61/H45 -> 2.7197637 | I119: =I61/I45 -> 2.992436 | J119: =J61/J45 -> 4.0780396
C120: Net Debt / EBITDA | E120: =E67/E45 -> -0.16631364 | F120: =F67/F45 -> -2.9738055 | G120: =G67/G45 -> 13.144054 | H120: =H67/H45 -> 5.726199 | I120: =I67/I45 -> 5.9957873 | J120: =J67/J45 -> 7.8673568
C121: Debt / Total Assets | E121: =E67/E58 -> 0.035347553 | F121: =F67/F58 -> 0.29260967 | G121: =G67/G58 -> 0.37604417 | H121: =H67/H58 -> 0.40143367 | I121: =I67/I58 -> 0.47181698 | J121: =J67/J58 -> 0.51440869
C122: Debt / Total Equity | E122: =E67/E74 -> 0.8473972 | F122: =F67/F74 -> 0.41364669 | G122: =G67/G74 -> 0.60267755 | H122: =H67/H74 -> 0.67065863 | I122: =I67/I74 -> 0.89328313 | J122: =J67/J74 -> 1.0593449
C124: COVERAGE
C125: EBITDA / Interest Expense | D125: =D45/D34 -> -4.1079255 | E125: =E45/E34 -> 2.4658633 | F125: =F45/F34 -> 29.821375 | G125: =G45/G34 -> -4.2356329 | H125: =H45/H34 -> -8.16631 | I125: =I45/I34 -> -7.0964362 | J125: =J45/J34 -> -4.9781808
C126: Operating Income / Interest Expense | D126: =D88/D34 -> -6.61423 | E126: =E88/E34 -> -0.21976822 | F126: =F88/F34 -> -10.326599 | G126: =G88/G34 -> -12.127039 | H126: =H88/H34 -> -12.538906 | I126: =I88/I34 -> -8.2001985 | J126: =J88/J34 -> -7.6701902
...

Sheet Pivot
B2: Sum of Value | C2: Column Labels
B3: Row Labels | C3: 2019-12-31 | D3: 2020-12-31 | E3: 2021-12-31 | F3: 2022-12-31 | G3: 2023-12-31 | H3: 2024-12-31 | I3: 2025-12-31
B4: Assets | D4: 276316182 | E4: 8266398000 | F4: 8893075000 | G4: 8817621000 | H4: 10992470000 | I4: 12467684000
B5: Cash | D5: 11630000 | E5: 42567000 | F5: 68079000 | G5: 104160000 | H5: 152089000 | I5: 194512000
B6: Compensation | C6: 111773000 | D6: 240731000 | E6: 1496988000 | F6: 894686000 | G6: 870642000 | H6: 1017483000 | I6: 1307040000
B7: DepreciationAndAmortization | C7: 0 | D7: 0 | E7: 113889000 | F7: 256909000 | G7: 300341000 | H7: 258256000 | I7: 358952000
B8: FinancingCashFlow | C8: -43007000 | D8: -295000 | E8: 1348151000 | F8: -217717000 | G8: -795033000 | H8: -313481000 | I8: -943038000
B9: GeneralAndAdministrativeExpense | C9: 51710000 | D9: 67811000 | E9: 140268000 | F9: 220610000 | G9: 242809000 | H9: 412931000 | I9: 747936000
B10: IncomeTaxExpense | C10: 240000 | D10: -102000 | E10: -65211000 | F10: -9380000 | G10: 25608000 | H10: 48782000 | I10: 42424000
B11: InterestExpense | C11: 6662000 | D11: 23816000 | E11: 27275000 | F11: 55711000 | G11: 75696000
B12: InvestingCashFlow | C12: -1173000 | D12: -652000 | E12: -1598872000 | F12: -485218000 | G12: -118031000 | H12: -638145000 | I12: -270571000
B13: Liabilities | D13: 9767101 | E13: 2418828000 | F13: 3344189000 | G13: 3539690000 | H13: 5186434000 | I13: 6413485000
B14: LongTermDebt | D14: 356386000 | E14: 1174167000 | F14: 1624771000 | G14: 1681241000 | H14: 2588496000 | I14: 3324426000
B15: NetIncomeLoss | C15: 22958000 | D15: -77831000 | E15: -376171000 | F15: -9289000 | G15: 54343000 | H15: 109584000 | I15: 78833000
B16: OperatingCashFlow | C16: 44064000 | D16: 5234000 | E16: 281658000 | F16: 728447000 | G16: 949145000 | H16: 999555000 | I16: 1256032000
B17: OperatingIncomeLoss | D17: -299659
B18: StockholdersEquity | D18: 5000001 | E18: 1663567000 | F18: 1604698000 | G18: 1528239000 | H18: 2127758000 | I18: 2205362000
B19: Revenue | C19: 190850000 | D19: 249815000 | E19: 823878000 | F19: 1369722000 | G19: 1731608000 | H19: 2295427000 | I19: 2870178000
B20: MinorityInterest | D20: 6526000 | E20: 4184003000 | F20: 3944188000 | G20: 3749692000 | H20: 3678278000 | I20: 3848837000
B21: ShareBasedCompensation | C21: 0 | D21: 0 | E21: 1205336000 | F21: 420832000 | G21: 312564000 | H21: 312609000 | I21: 673524000
B22: RepaymentsOfDebt | C22: 83590000 | D22: 171458000 | E22: 577835000 | F22: 323000000 | G22: 1000000000 | H22: 1245000000 | I22: 1540000000
B23: DividendsPaid | C23: 0 | D23: 0 | E23: 47076000 | F23: 182550000 | G23: 247882000 | H23: 368331000 | I23: 546657000
B24: EPSDiluted | E24: -1.34 | F24: -0.02 | G24: 0.1 | H24: 0.2 | I24: 0.1
B25: ProceedsFromDebt | C25: 344944000 | D25: 240547000 | E25: 1390296000 | F25: 775060000 | G25: 1054800000 | H25: 2170000000 | I25: 2270000000
B26: ProceedsFromEquity | D26: 269500000
B27: DebtFairValue | F27: 1300000000 | G27: 1400000000 | H27: 2500000000 | I27: 3200000000
B28: ConsolidatedNetIncome | C28: 20465000 | D28: -82441000 | E28: -1802266000 | F28: -40235000 | G28: 220776000 | H28: 420446000 | I28: 305487000
B29: Depreciation | C29: 829000 | D29: 673000 | E29: 665000 | F29: 2304000 | G29: 10226000 | H29: 16660000 | I29: 23446000
B30: PPENet | D30: 3356000 | E30: 7951000 | F30: 71190000 | G30: 134893000 | H30: 187749000 | I30: 218941000
B31: InterestAndDividendIncome | E31: 387000 | F31: 4357000 | G31: 22176000 | H31: 42172000 | I31: 45184000
B32: GainLossOnInvestments | C32: 0 | D32: 0 | E32: -3526000 | F32: -132000 | G32: 4203000 | H32: 1713000 | I32: -7105000
B33: Investments | D33: 2678000 | E33: 12143000 | F33: 317231000 | G33: 344265000 | H33: 486945000 | I33: 484389000
B34: DueFromRelatedParties | D34: 92698000 | E34: 224576000 | F34: 357921000
B35: Goodwill | D35: 0 | E35: 4132245000 | F35: 4205159000 | G35: 4224153000 | H35: 4699465000 | I35: 5624469000
B36: OtherAssets | D36: 16469000 | E36: 38620000 | F36: 99679000 | G36: 187455000 | H36: 258748000 | I36: 382519000
B37: IntangibleAssetsNet | D37: 0 | E37: 2611411000 | F37: 2405422000 | G37: 2110008000 | H37: 2902752000 | I37: 2888800000
B38: AccruedCompensation | D38: 207957000 | E38: 155606000 | F38: 309644000 | G38: 370726000 | H38: 424024000 | I38: 525550000
B39: AccountsPayableAndOther | D39: 58415000 | E39: 68339000 | F39: 126559000 | G39: 138754000 | H39: 165953000 | I39: 163000000
B40: DeferredTaxLiabilities | D40: 0 | E40: 48962000 | F40: 41791000 | G40: 34419000 | H40: 36867000 | I40: 39663000
B41: AdditionalPaidInCapital | D41: 5260809 | E41: 2160934000 | F41: 2293903000 | G41: 2410982000 | H41: 3269239000 | I41: 3812770000
B42: AccumulatedDeficit | D42: -261631 | E42: -497506000 | F42: -689345000 | G42: -882884000 | H42: -1141631000 | I42: -1609455000
B43: OperatingLeaseRightOfUseAsset | D43: 0 | E43: 86033000 | F43: 224411000 | G43: 281669000 | H43: 325090000 | I43: 456204000
B44: OperatingLeaseLiability | D44: 0 | E44: 88480000 | F44: 239844000 | G44: 319532000 | H44: 390353000 | I44: 538147000
B45: CapEx | C45: 1173000 | D45: 652000 | E45: 5261000 | F45: 65539000 | G45: 67905000 | H45: 64187000 | I45: 57748000
B46: AcquisitionPayments | C46: 0 | D46: 0 | E46: 1578866000 | F46: 114454000 | G46: 26265000 | H46: 445210000 | I46: 244580000

Sheet Query
A1: Metric | B1: Date | C1: Value
A2: Revenue | B2: 2019-12-31 | C2: 190850000
A3: Revenue | B3: 2020-12-31 | C3: 249815000
A4: Revenue | B4: 2021-12-31 | C4: 823878000
A5: Revenue | B5: 2022-12-31 | C5: 1369722000
A6: Revenue | B6: 2023-12-31 | C6: 1731608000
A7: Revenue | B7: 2024-12-31 | C7: 2295427000
A8: Revenue | B8: 2025-12-31 | C8: 2870178000
A9: NetIncomeLoss | B9: 2019-12-31 | C9: 22958000
A10: NetIncomeLoss | B10: 2020-12-31 | C10: -77831000
A11: NetIncomeLoss | B11: 2021-12-31 | C11: -376171000
A12: NetIncomeLoss | B12: 2022-12-31 | C12: -9289000
A13: NetIncomeLoss | B13: 2023-12-31 | C13: 54343000
... A263: AcquisitionPayments | B263: 2025-12-31 | C263: 244580000

Sheet Sheet1
B2: CFA Template | C2: Blue Owl Equivalent | E2: https://www.sec.gov/ix?doc=/Archives/edgar/data/0001823945/000182394526000009/owl-20251231.htm#fact-identifier-32
B3: Equity Capital | C3: Additional Paid-in Capital
B4: Retained Earnings | C4: Accumulated Deficit
B5: Shareholder's Equity | C5: Total Shareholders' Equity - Blue Owl
B6: Total Liabilities & Shareholder's Equity | C6: Total Liabilities & Shareholder's Equity
B8: Other Non-Cash & WC Changes
B9: Non-cash items:
B10: Amortization of debt discounts
B11: Non-cash interest income
B12: Deferred income taxes
B13: Change in TRA liability
B14: Change in warrant liability
B15: Change in earnout liability
B16: Net gains/losses on investments
B18: Working capital changes:
B19: Due from related parties
B20: Other assets
... B25: other names for these;
B26: Duefromrelatedparties | C26: OtherReceivables
B27: InterestExpense | C27: InterestExpenseNonoperating
B28: Other Financing Items plug handles everything else
B30: 2026 Q1 Deck
B31: RSU tax withholding ($79.6M in 2025)
B32: TRA payments ($53.5M in 2025)
B33: Share repurchases ($53.7M in 2025)
B34: Debt issuance costs ($3.4M in 2025)
B35: Earnout payments ($36.8M in 2025)
B37: Revenue Forecast | D37: Bottom-up AUM
B38: Revenue ≈ Fee-Paying AUM × Average Fee Rate
B39: From BlueOwl Q1 2026 deck:
B40: AUM: | C40: $315B
B41: Fee-Paying AUM (FPAUM): | C41: $225B | D41: (this is the number that actually matters)
B42: LTM FRE Management Fees: | C42: $2,622M
B43: So implied fee rate = $2,622M / $225B ≈ 1.17% | C43: 0.0117
